[
  {
    "accuracy": 0.86,
    "calibration_gap": 0.05,
    "decay_risk_score": 0.026667,
    "high_calibration_drift": 0,
    "high_input_drift": 0,
    "high_label_drift": 0,
    "high_override_rate": 0,
    "high_performance_decay": 0,
    "high_subgroup_gap": 0,
    "input_drift": 0.0,
    "interpretation": "Model decay risk rises when data drift, label drift, performance loss, calibration drift, subgroup gaps, or override rates increase.",
    "label_drift": 0.0,
    "override_rate": 0.04,
    "performance_decay": 0.0,
    "period": "baseline",
    "status": "pass",
    "subgroup_gap": 0.07
  },
  {
    "accuracy": 0.84,
    "calibration_gap": 0.06,
    "decay_risk_score": 0.061667,
    "high_calibration_drift": 0,
    "high_input_drift": 0,
    "high_label_drift": 0,
    "high_override_rate": 0,
    "high_performance_decay": 0,
    "high_subgroup_gap": 0,
    "input_drift": 0.12,
    "interpretation": "Model decay risk rises when data drift, label drift, performance loss, calibration drift, subgroup gaps, or override rates increase.",
    "label_drift": 0.04,
    "override_rate": 0.05,
    "performance_decay": 0.02,
    "period": "month_1",
    "status": "pass",
    "subgroup_gap": 0.08
  },
  {
    "accuracy": 0.81,
    "calibration_gap": 0.09,
    "decay_risk_score": 0.108333,
    "high_calibration_drift": 0,
    "high_input_drift": 0,
    "high_label_drift": 0,
    "high_override_rate": 0,
    "high_performance_decay": 0,
    "high_subgroup_gap": 0,
    "input_drift": 0.23,
    "interpretation": "Model decay risk rises when data drift, label drift, performance loss, calibration drift, subgroup gaps, or override rates increase.",
    "label_drift": 0.1,
    "override_rate": 0.07,
    "performance_decay": 0.05,
    "period": "month_2",
    "status": "pass",
    "subgroup_gap": 0.11
  },
  {
    "accuracy": 0.76,
    "calibration_gap": 0.14,
    "decay_risk_score": 0.161667,
    "high_calibration_drift": 1,
    "high_input_drift": 1,
    "high_label_drift": 1,
    "high_override_rate": 0,
    "high_performance_decay": 1,
    "high_subgroup_gap": 1,
    "input_drift": 0.31,
    "interpretation": "Model decay risk rises when data drift, label drift, performance loss, calibration drift, subgroup gaps, or override rates increase.",
    "label_drift": 0.16,
    "override_rate": 0.11,
    "performance_decay": 0.1,
    "period": "month_3",
    "status": "escalate",
    "subgroup_gap": 0.15
  },
  {
    "accuracy": 0.73,
    "calibration_gap": 0.18,
    "decay_risk_score": 0.203333,
    "high_calibration_drift": 1,
    "high_input_drift": 1,
    "high_label_drift": 1,
    "high_override_rate": 1,
    "high_performance_decay": 1,
    "high_subgroup_gap": 1,
    "input_drift": 0.38,
    "interpretation": "Model decay risk rises when data drift, label drift, performance loss, calibration drift, subgroup gaps, or override rates increase.",
    "label_drift": 0.19,
    "override_rate": 0.16,
    "performance_decay": 0.13,
    "period": "month_4",
    "status": "escalate",
    "subgroup_gap": 0.18
  },
  {
    "accuracy": 0.7,
    "calibration_gap": 0.21,
    "decay_risk_score": 0.238333,
    "high_calibration_drift": 1,
    "high_input_drift": 1,
    "high_label_drift": 1,
    "high_override_rate": 1,
    "high_performance_decay": 1,
    "high_subgroup_gap": 1,
    "input_drift": 0.42,
    "interpretation": "Model decay risk rises when data drift, label drift, performance loss, calibration drift, subgroup gaps, or override rates increase.",
    "label_drift": 0.23,
    "override_rate": 0.19,
    "performance_decay": 0.16,
    "period": "month_5",
    "status": "escalate",
    "subgroup_gap": 0.22
  }
]